ai_intro/__init__.py
ai_intro/_modidx.py
ai_intro/_nbdev.py
ai_intro/core.py
ai_intro/maskrcnn_inference.py
ai_intro/maskrcnn_train.py
ai_intro/mlp-learning.py
ai_intro/search.py
ai_intro/taxi_problem.py
ai_intro-0.0.1.dist-info/LICENSE
ai_intro-0.0.1.dist-info/METADATA
ai_intro-0.0.1.dist-info/WHEEL
ai_intro-0.0.1.dist-info/entry_points.txt
ai_intro-0.0.1.dist-info/top_level.txt
ai_intro-0.0.1.dist-info/RECORD
