Metadata-Version: 2.1
Name: ai-intro
Version: 0.0.1
Summary: A repo for course ai intro
Home-page: https://github.com/ARG-NCTU/ai_intro/tree/master/
Author: hchengwang
Author-email: hchengwang@gmail.com
License: Apache Software License 2.0
Keywords: course ai intro
Platform: UNKNOWN
Classifier: Development Status :: 3 - Alpha
Classifier: Intended Audience :: Developers
Classifier: Natural Language :: English
Classifier: Programming Language :: Python :: 3.6
Classifier: Programming Language :: Python :: 3.7
Classifier: Programming Language :: Python :: 3.8
Classifier: Programming Language :: Python :: 3.9
Classifier: Programming Language :: Python :: 3.10
Classifier: License :: OSI Approved :: Apache Software License
Requires-Python: >=3.6
License-File: LICENSE
Requires-Dist: pip
Requires-Dist: packaging
Provides-Extra: dev
